Workbook

Sheet COMO SE USA
A1: Hoja de mermas
A2: El Metodo 360 · elmetodo360.com
B5: Los cinco principios
A6: 1 | B6: El precio del albaran no es el precio del plato. | C6: Si de un kilo de merluza aprovechas 620 gramos, el kilo util te cuesta un 61 % mas de lo que pone la factura. Los escandallos hechos con el precio del albaran mienten, y mienten siempre a la baja.
A7: 2 | B7: El rendimiento se mide una vez; el desperdicio, todos los dias. | C7: Pesa el producto entero, limpialo, pesa lo aprovechable y guarda ese factor. No hace falta repetirlo salvo que cambies de proveedor o de calibre.
A8: 3 | B8: Sin motivo, el dato no sirve. | C8: Apuntar 'dos kilos de tomate' no arregla nada. Apuntar 'dos kilos de tomate, caducado' te dice que compras de mas. 'Error de cocina' te dice que hay que formar. Es el motivo lo que se corrige, no el kilo.
A9: 4 | B9: Si no hubo merma, se escribe cero. | C9: Un dia en blanco no significa que no se tirara nada: significa que nadie lo apunto. El cero es un dato; el hueco, no.
A10: 5 | B10: Se cuenta en euros, no en kilos. | C10: Tres kilos de patata y trescientos gramos de solomillo no son comparables en peso, pero si en dinero. La hoja lo convierte sola.
B12: RENDIMIENTO: se hace una vez por producto. Pesa entero, limpia, pesa lo aprovechable. La hoja te da el coste real del kilo util, que es el que va al escandallo.
B13: PARTE DIARIO: se rellena al cerrar, con el producto, la cantidad y el motivo. El coste sale solo si el producto esta en la pestana RENDIMIENTO.
B14: RESUMEN: no se toca. Dice por que motivo se te va el dinero y que producto lo lidera.

Sheet RENDIMIENTO
A1: Rendimiento por producto
A2: Se mide una vez. El coste del kilo util es el que va al escandallo.
A5: Producto | B5: Unidad | C5: Peso bruto | D5: Peso limpio | E5: Coste del bruto | F5: Rendimiento | G5: Coste del kilo util | H5: Sobrecoste
F6: =IF(N(C6)=0,"",D6/C6) | G6: =IF(N(D6)=0,"",E6/(D6/C6)) | H6: =IF(N(E6)=0,"",(G6-E6)/E6)
F7: =IF(N(C7)=0,"",D7/C7) | G7: =IF(N(D7)=0,"",E7/(D7/C7)) | H7: =IF(N(E7)=0,"",(G7-E7)/E7)
F8: =IF(N(C8)=0,"",D8/C8) | G8: =IF(N(D8)=0,"",E8/(D8/C8)) | H8: =IF(N(E8)=0,"",(G8-E8)/E8)
F9: =IF(N(C9)=0,"",D9/C9) | G9: =IF(N(D9)=0,"",E9/(D9/C9)) | H9: =IF(N(E9)=0,"",(G9-E9)/E9)
F10: =IF(N(C10)=0,"",D10/C10) | G10: =IF(N(D10)=0,"",E10/(D10/C10)) | H10: =IF(N(E10)=0,"",(G10-E10)/E10)
F11: =IF(N(C11)=0,"",D11/C11) | G11: =IF(N(D11)=0,"",E11/(D11/C11)) | H11: =IF(N(E11)=0,"",(G11-E11)/E11)
F12: =IF(N(C12)=0,"",D12/C12) | G12: =IF(N(D12)=0,"",E12/(D12/C12)) | H12: =IF(N(E12)=0,"",(G12-E12)/E12)
F13: =IF(N(C13)=0,"",D13/C13) | G13: =IF(N(D13)=0,"",E13/(D13/C13)) | H13: =IF(N(E13)=0,"",(G13-E13)/E13)
F14: =IF(N(C14)=0,"",D14/C14) | G14: =IF(N(D14)=0,"",E14/(D14/C14)) | H14: =IF(N(E14)=0,"",(G14-E14)/E14)
F15: =IF(N(C15)=0,"",D15/C15) | G15: =IF(N(D15)=0,"",E15/(D15/C15)) | H15: =IF(N(E15)=0,"",(G15-E15)/E15)
F16: =IF(N(C16)=0,"",D16/C16) | G16: =IF(N(D16)=0,"",E16/(D16/C16)) | H16: =IF(N(E16)=0,"",(G16-E16)/E16)
F17: =IF(N(C17)=0,"",D17/C17) | G17: =IF(N(D17)=0,"",E17/(D17/C17)) | H17: =IF(N(E17)=0,"",(G17-E17)/E17)
... F45: =IF(N(C45)=0,"",D45/C45) | G45: =IF(N(D45)=0,"",E45/(D45/C45)) | H45: =IF(N(E45)=0,"",(G45-E45)/E45)

Sheet PARTE DIARIO
A1: Parte diario de mermas
A2: Se rellena al cerrar. Si no hubo merma, se escribe cero.
A5: Fecha | B5: Producto | C5: Unidad | D5: Cantidad | E5: Motivo | F5: Coste unidad | G5: Coste
G6: =IF(N(D6)*N(F6)=0,"",D6*F6)
G7: =IF(N(D7)*N(F7)=0,"",D7*F7)
G8: =IF(N(D8)*N(F8)=0,"",D8*F8)
G9: =IF(N(D9)*N(F9)=0,"",D9*F9)
G10: =IF(N(D10)*N(F10)=0,"",D10*F10)
G11: =IF(N(D11)*N(F11)=0,"",D11*F11)
G12: =IF(N(D12)*N(F12)=0,"",D12*F12)
G13: =IF(N(D13)*N(F13)=0,"",D13*F13)
G14: =IF(N(D14)*N(F14)=0,"",D14*F14)
G15: =IF(N(D15)*N(F15)=0,"",D15*F15)
G16: =IF(N(D16)*N(F16)=0,"",D16*F16)
G17: =IF(N(D17)*N(F17)=0,"",D17*F17)
... G125: =IF(N(D125)*N(F125)=0,"",D125*F125)
F127: TOTAL MERMA | G127: =SUM(G6:G125)
A129: El coste unidad de un producto con merma de limpieza es el del kilo util (columna G de RENDIMIENTO), no el del albaran.

Sheet RESUMEN
A1: Donde se te va
A2: No se toca: se lee.
B5: Por motivo
B6: Motivo | C6: Euros | D6: % del total | E6: Que significa
B7: Caducado | C7: =SUMIF('PARTE DIARIO'!$E$6:$E$125,B7,'PARTE DIARIO'!$G$6:$G$125) | D7: =IF('PARTE DIARIO'!$G$127=0,"",C7/'PARTE DIARIO'!$G$127) | E7: Compras de mas o rotas mal el genero. Mira el inventario antes de pedir.
B8: Mal conservado | C8: =SUMIF('PARTE DIARIO'!$E$6:$E$125,B8,'PARTE DIARIO'!$G$6:$G$125) | D8: =IF('PARTE DIARIO'!$G$127=0,"",C8/'PARTE DIARIO'!$G$127) | E8: Cadena de frio o tapado. Es el mas caro y el mas facil de corregir.
B9: Error de cocina | C9: =SUMIF('PARTE DIARIO'!$E$6:$E$125,B9,'PARTE DIARIO'!$G$6:$G$125) | D9: =IF('PARTE DIARIO'!$G$127=0,"",C9/'PARTE DIARIO'!$G$127) | E9: Formacion o ficha tecnica. Si se repite el mismo plato, es la receta.
B10: Rotura | C10: =SUMIF('PARTE DIARIO'!$E$6:$E$125,B10,'PARTE DIARIO'!$G$6:$G$125) | D10: =IF('PARTE DIARIO'!$G$127=0,"",C10/'PARTE DIARIO'!$G$127) | E10: Manipulacion o material. Si sube en fin de semana, es prisa.
B11: Devuelto por cliente | C11: =SUMIF('PARTE DIARIO'!$E$6:$E$125,B11,'PARTE DIARIO'!$G$6:$G$125) | D11: =IF('PARTE DIARIO'!$G$127=0,"",C11/'PARTE DIARIO'!$G$127) | E11: Mira si se concentra en un plato: ahi tienes un problema de carta.
B12: Comida de personal | C12: =SUMIF('PARTE DIARIO'!$E$6:$E$125,B12,'PARTE DIARIO'!$G$6:$G$125) | D12: =IF('PARTE DIARIO'!$G$127=0,"",C12/'PARTE DIARIO'!$G$127) | E12: No es merma si esta prevista. Si no lo esta, es un coste oculto.
B13: Prueba o cata | C13: =SUMIF('PARTE DIARIO'!$E$6:$E$125,B13,'PARTE DIARIO'!$G$6:$G$125) | D13: =IF('PARTE DIARIO'!$G$127=0,"",C13/'PARTE DIARIO'!$G$127) | E13: Inversion, no perdida. Pero se cuenta igual.
B16: La merma sobre tus ventas
B17: Merma del periodo | C17: ='PARTE DIARIO'!G127 | E17: Sale sola del parte.
B18: Venta del periodo (sin IVA) | C18: 0 | E18: La pones tu, del TPV.
B19: Merma sobre venta | C19: =IF(N(C18)=0,"",C17/C18) | E19: El numero que se compara mes a mes.
B22: Como se lee
B23: Por debajo del 1 % | E23: Estas bien. Sigue apuntando para que siga asi.
B24: Entre el 1 y el 3 % | E24: Lo normal en un local que no la vigila. Ataca el motivo que mas pese: casi siempre es caducado, y casi siempre se arregla pidiendo menos y mas veces.
B25: Por encima del 3 % | E25: Ahi tienes el margen que echas de menos. Con una venta de 30.000 al mes, cada punto de merma son 300 euros que se van a la basura todos los meses.

Sheet EJEMPLO rendimiento
A1: Rendimiento por producto
A2: Se mide una vez. El coste del kilo util es el que va al escandallo.
A5: Producto | B5: Unidad | C5: Peso bruto | D5: Peso limpio | E5: Coste del bruto | F5: Rendimiento | G5: Coste del kilo util | H5: Sobrecoste
A6: Merluza del pincho | B6: kg | C6: 1 | D6: 0.62 | E6: 14.8 | F6: =IF(N(C6)=0,"",D6/C6) | G6: =IF(N(D6)=0,"",E6/(D6/C6)) | H6: =IF(N(E6)=0,"",(G6-E6)/E6)
A7: Solomillo de ternera | B7: kg | C7: 1 | D7: 0.85 | E7: 18.9 | F7: =IF(N(C7)=0,"",D7/C7) | G7: =IF(N(D7)=0,"",E7/(D7/C7)) | H7: =IF(N(E7)=0,"",(G7-E7)/E7)
A8: Pulpo cocido | B8: kg | C8: 1 | D8: 0.78 | E8: 22 | F8: =IF(N(C8)=0,"",D8/C8) | G8: =IF(N(D8)=0,"",E8/(D8/C8)) | H8: =IF(N(E8)=0,"",(G8-E8)/E8)
A9: Alcachofa fresca | B9: kg | C9: 1 | D9: 0.38 | E9: 4.6 | F9: =IF(N(C9)=0,"",D9/C9) | G9: =IF(N(D9)=0,"",E9/(D9/C9)) | H9: =IF(N(E9)=0,"",(G9-E9)/E9)
A10: Pina | B10: kg | C10: 1 | D10: 0.5 | E10: 1.95 | F10: =IF(N(C10)=0,"",D10/C10) | G10: =IF(N(D10)=0,"",E10/(D10/C10)) | H10: =IF(N(E10)=0,"",(G10-E10)/E10)
A11: Lubina entera | B11: kg | C11: 1 | D11: 0.45 | E11: 12.5 | F11: =IF(N(C11)=0,"",D11/C11) | G11: =IF(N(D11)=0,"",E11/(D11/C11)) | H11: =IF(N(E11)=0,"",(G11-E11)/E11)
F12: =IF(N(C12)=0,"",D12/C12) | G12: =IF(N(D12)=0,"",E12/(D12/C12)) | H12: =IF(N(E12)=0,"",(G12-E12)/E12)
F13: =IF(N(C13)=0,"",D13/C13) | G13: =IF(N(D13)=0,"",E13/(D13/C13)) | H13: =IF(N(E13)=0,"",(G13-E13)/E13)

Sheet EJEMPLO parte
A1: Parte diario de mermas
A2: Se rellena al cerrar. Si no hubo merma, se escribe cero.
A5: Fecha | B5: Producto | C5: Unidad | D5: Cantidad | E5: Motivo | F5: Coste unidad | G5: Coste
A6: 2026-09-01 | B6: Merluza del pincho | C6: kg | D6: 0.8 | E6: Mal conservado | F6: 23.87 | G6: =IF(N(D6)*N(F6)=0,"",D6*F6)
A7: 2026-09-01 | B7: Tomate rama | C7: kg | D7: 2 | E7: Caducado | F7: 1.85 | G7: =IF(N(D7)*N(F7)=0,"",D7*F7)
A8: 2026-09-02 | B8: Solomillo de ternera | C8: kg | D8: 0.3 | E8: Error de cocina | F8: 22.24 | G8: =IF(N(D8)*N(F8)=0,"",D8*F8)
A9: 2026-09-02 | B9: Pan de cristal | C9: unidad | D9: 6 | E9: Caducado | F9: 0.85 | G9: =IF(N(D9)*N(F9)=0,"",D9*F9)
A10: 2026-09-03 | B10: Vino tinto copa | C10: unidad | D10: 2 | E10: Devuelto por cliente | F10: 1.9 | G10: =IF(N(D10)*N(F10)=0,"",D10*F10)
G11: =IF(N(D11)*N(F11)=0,"",D11*F11)
G12: =IF(N(D12)*N(F12)=0,"",D12*F12)
G13: =IF(N(D13)*N(F13)=0,"",D13*F13)
F15: TOTAL MERMA | G15: =SUM(G6:G13)
A17: El coste unidad de un producto con merma de limpieza es el del kilo util (columna G de RENDIMIENTO), no el del albaran.
